instats/__init__.py
instats/engagement.py
instats/feedmatch.py
instats/feedmatch_utils.py
instats/instatsprofile.py
instats/timeofpost.py
instats-2.0.0.dist-info/LICENSE.txt
instats-2.0.0.dist-info/METADATA
instats-2.0.0.dist-info/WHEEL
instats-2.0.0.dist-info/top_level.txt
instats-2.0.0.dist-info/RECORD
