Metadata-Version: 2.1
Name: instats
Version: 2.0.0
Summary: Package for processing statistics from Instagram profiles
Home-page: https://github.com/nramkissoon/Instats
Author: Nicholas Ramkissoon
License: UNKNOWN
Platform: UNKNOWN
Classifier: Intended Audience :: Developers
Classifier: Programming Language :: Python :: 3
Classifier: License :: OSI Approved :: MIT License
Classifier: Operating System :: OS Independent
Requires-Python: >=3
